myfunctions_AdnanGrifat/__init__.py
myfunctions_AdnanGrifat/math.py
myfunctions_AdnanGrifat-0.0.19.dist-info/METADATA
myfunctions_AdnanGrifat-0.0.19.dist-info/WHEEL
myfunctions_AdnanGrifat-0.0.19.dist-info/top_level.txt
myfunctions_AdnanGrifat-0.0.19.dist-info/RECORD
