Metadata-Version: 2.1
Name: myfunctions-AdnanGrifat
Version: 0.0.19
Summary: A description of your package
Home-page: https://github.com/AdnanGrifat/
Author: Adnan Grifat
Author-email: grifat1978@gmail.com
License: MIT
Platform: UNKNOWN
Classifier: Programming Language :: Python :: 3
Classifier: License :: OSI Approved :: MIT License
Classifier: Operating System :: OS Independent
Requires-Python: >=3.6
